{
  "pools": [
    {
      "rolls": 1,
      "entries": [
        {
          "type": "minecraft:loot_table",
          "value": "pirates:mermaid_meat",
          "functions": [
            {
              "function": "minecraft:set_count",
              "count": {
                "min": 0,
                "max": 2
              }
            }
          ]
        }
      ]
    },
    {
      "rolls": 1,
      "entries": [
        {
          "type": "minecraft:loot_table",
          "value": "pirates:mermaid_scales"
        }
      ],
      "conditions": [
        {
          "condition": "minecraft:random_chance",
          "chance": 0.8
        }
      ]
    }
  ]
}
